Kala_Quantum/__init__.py
Kala_Quantum/datasets.py
Kala_Quantum/models.py
Kala_Quantum/quantum_core.py
Kala_Quantum/quantum_layer.py
Kala_Quantum/tokenizer.py
Kala_Quantum/train.py
Kala_Quantum_185-0.1.3.dist-info/METADATA
Kala_Quantum_185-0.1.3.dist-info/WHEEL
Kala_Quantum_185-0.1.3.dist-info/top_level.txt
Kala_Quantum_185-0.1.3.dist-info/RECORD
