Metadata-Version: 2.1
Name: Kala_Quantum_185
Version: 0.1.3
Summary: A hybrid classical-quantum framework for code language modeling.
Home-page: https://github.com/kalasaikamesh944/kala_quantum
Author: N V R K SAI KAMESH YADAVALLI
Author-email: saikamesh.y@gmail.com
License: MIT
Classifier: Programming Language :: Python :: 3
Classifier: License :: OSI Approved :: MIT License
Classifier: Operating System :: OS Independent
Requires-Python: >=3.6
Requires-Dist: numpy>=1.21.0
Requires-Dist: torch>=1.12.0
